onyx/__init__.py
onyx/bossbar.py
onyx/class_types.py
onyx/commands.py
onyx/dev_util.py
onyx/execute.py
onyx/pack_manager.py
onyx/registries.py
onyx/scoreboard.py
onyx/selector.py
onyx/storage.py
onyx/text_component.py
onyx/util.py
onyx/split_registries/__init__.py
onyx/split_registries/biome.py
onyx/split_registries/block.py
onyx/split_registries/block_tag.py
onyx/split_registries/effect.py
onyx/split_registries/enchantment.py
onyx/split_registries/entity.py
onyx/split_registries/entity_tag.py
onyx/split_registries/gamerule.py
onyx/split_registries/item.py
onyx/split_registries/item_tag.py
onyx/split_registries/particle.py
onyx/split_registries/recipe.py
onyx/split_registries/refresh.py
onyx/split_registries/structure.py
onyx_mclib-2.1.3.dist-info/LICENSE
onyx_mclib-2.1.3.dist-info/METADATA
onyx_mclib-2.1.3.dist-info/WHEEL
onyx_mclib-2.1.3.dist-info/top_level.txt
onyx_mclib-2.1.3.dist-info/RECORD
