Metadata-Version: 2.1
Name: onyx-mclib
Version: 2.1.3
Summary: A python library to create minecraft data packs
Home-page: https://github.com/DoubleF3lix/Onyx/
License: UNKNOWN
Platform: UNKNOWN
Classifier: Programming Language :: Python :: 3
Classifier: License :: OSI Approved :: MIT License
Classifier: Operating System :: OS Independent
Requires-Python: >=3.6
License-File: LICENSE
